{
	"class": "Module",
	"id": "node_11300",
	"inlets": [
		{
			"assist": "in1",
			"default": 0
		}
	],
	"outlets": [
		{
			"assist": "out1"
		},
		{
			"assist": "out2"
		},
		{
			"assist": "led1"
		},
		{
			"assist": "led2"
		},
		{
			"assist": "led3"
		},
		{
			"assist": "led4"
		}
	],
	"imports": {
		
	},
	"functions": {
		
	},
	"block": {
		"class": "Block",
		"id": "node_11823",
		"children": [
			{
				"class": "Declaration",
				"id": "node_11338",
				"name": "delay_489",
				"inputs": [
					{
						"class": "Constant",
						"id": "node_11339",
						"value": "3840",
						"eval": 3840,
						"type": "constant int",
						"source": "box: [delay 3840 $in1 $in2] => tap_490"
					}
				],
				"attributes": {
					
				},
				"type": "init Delay",
				"typename": "Delay",
				"source": "box: [delay 3840 $in1 $in2] => tap_490"
			},
			{
				"class": "Declaration",
				"id": "node_11336",
				"name": "delay_484",
				"inputs": [
					{
						"class": "Constant",
						"id": "node_11337",
						"value": "3940",
						"eval": 3940,
						"type": "constant int",
						"source": "box: [delay 3940 $in1 $in2] => tap_485"
					}
				],
				"attributes": {
					
				},
				"type": "init Delay",
				"typename": "Delay",
				"source": "box: [delay 3940 $in1 $in2] => tap_485"
			},
			{
				"class": "Declaration",
				"id": "node_11334",
				"name": "history_517",
				"inputs": [
					{
						"class": "Constant",
						"id": "node_11335",
						"value": "0",
						"eval": 0,
						"type": "constant int",
						"source": "box: [history history_444 0 $in1] => history_444"
					}
				],
				"attributes": {
					
				},
				"type": "signal t_sample",
				"typename": "History",
				"source": "source: [gen $in1 @file oopsy.ctrl.smooth3] => gen_453 parent: box: [history history_444 0 $in1] => history_444"
			},
			{
				"class": "Declaration",
				"id": "node_11332",
				"name": "history_518",
				"inputs": [
					{
						"class": "Constant",
						"id": "node_11333",
						"value": "0",
						"eval": 0,
						"type": "constant int",
						"source": "box: [history history_446 0 $in1] => history_446"
					}
				],
				"attributes": {
					
				},
				"type": "signal t_sample",
				"typename": "History",
				"source": "source: [gen $in1 @file oopsy.ctrl.smooth3] => gen_453 parent: box: [history history_446 0 $in1] => history_446"
			},
			{
				"class": "Declaration",
				"id": "node_11330",
				"name": "history_516",
				"inputs": [
					{
						"class": "Constant",
						"id": "node_11331",
						"value": "0",
						"eval": 0,
						"type": "constant int",
						"source": "box: [history history_448 0 $in1] => history_448"
					}
				],
				"attributes": {
					
				},
				"type": "signal t_sample",
				"typename": "History",
				"source": "source: [gen $in1 @file oopsy.ctrl.smooth3] => gen_453 parent: box: [history history_448 0 $in1] => history_448"
			},
			{
				"class": "Declaration",
				"id": "node_11328",
				"name": "delay_463",
				"inputs": [
					{
						"class": "Constant",
						"id": "node_11329",
						"value": "3840",
						"eval": 3840,
						"type": "constant int",
						"source": "box: [delay 3840 $in1 $in2] => tap_464"
					}
				],
				"attributes": {
					
				},
				"type": "init Delay",
				"typename": "Delay",
				"source": "box: [delay 3840 $in1 $in2] => tap_464"
			},
			{
				"class": "Declaration",
				"id": "node_11326",
				"name": "history_504",
				"inputs": [
					{
						"class": "Constant",
						"id": "node_11327",
						"value": "0",
						"eval": 0,
						"type": "constant int",
						"source": "box: [history history_444 0 $in1] => history_444"
					}
				],
				"attributes": {
					
				},
				"type": "signal t_sample",
				"typename": "History",
				"source": "source: [gen $in1 @file oopsy.ctrl.smooth3] => gen_455 parent: box: [history history_444 0 $in1] => history_444"
			},
			{
				"class": "Declaration",
				"id": "node_11324",
				"name": "history_505",
				"inputs": [
					{
						"class": "Constant",
						"id": "node_11325",
						"value": "0",
						"eval": 0,
						"type": "constant int",
						"source": "box: [history history_446 0 $in1] => history_446"
					}
				],
				"attributes": {
					
				},
				"type": "signal t_sample",
				"typename": "History",
				"source": "source: [gen $in1 @file oopsy.ctrl.smooth3] => gen_455 parent: box: [history history_446 0 $in1] => history_446"
			},
			{
				"class": "Declaration",
				"id": "node_11322",
				"name": "history_503",
				"inputs": [
					{
						"class": "Constant",
						"id": "node_11323",
						"value": "0",
						"eval": 0,
						"type": "constant int",
						"source": "box: [history history_448 0 $in1] => history_448"
					}
				],
				"attributes": {
					
				},
				"type": "signal t_sample",
				"typename": "History",
				"source": "source: [gen $in1 @file oopsy.ctrl.smooth3] => gen_455 parent: box: [history history_448 0 $in1] => history_448"
			},
			{
				"class": "Declaration",
				"id": "node_11320",
				"name": "history_444",
				"inputs": [
					{
						"class": "Constant",
						"id": "node_11321",
						"value": "0",
						"eval": 0,
						"type": "constant int",
						"source": "box: [history history_444 0 $in1] => history_444"
					}
				],
				"attributes": {
					
				},
				"type": "signal t_sample",
				"typename": "History",
				"source": "source: [gen $in1 @file oopsy.ctrl.smooth3] => gen_454 parent: box: [history history_444 0 $in1] => history_444"
			},
			{
				"class": "Declaration",
				"id": "node_11318",
				"name": "history_446",
				"inputs": [
					{
						"class": "Constant",
						"id": "node_11319",
						"value": "0",
						"eval": 0,
						"type": "constant int",
						"source": "box: [history history_446 0 $in1] => history_446"
					}
				],
				"attributes": {
					
				},
				"type": "signal t_sample",
				"typename": "History",
				"source": "source: [gen $in1 @file oopsy.ctrl.smooth3] => gen_454 parent: box: [history history_446 0 $in1] => history_446"
			},
			{
				"class": "Declaration",
				"id": "node_11316",
				"name": "history_448",
				"inputs": [
					{
						"class": "Constant",
						"id": "node_11317",
						"value": "0",
						"eval": 0,
						"type": "constant int",
						"source": "box: [history history_448 0 $in1] => history_448"
					}
				],
				"attributes": {
					
				},
				"type": "signal t_sample",
				"typename": "History",
				"source": "source: [gen $in1 @file oopsy.ctrl.smooth3] => gen_454 parent: box: [history history_448 0 $in1] => history_448"
			},
			{
				"class": "Declaration",
				"id": "node_11314",
				"name": "sw5",
				"inputs": [
					{
						"class": "Constant",
						"id": "node_11315",
						"value": "0",
						"eval": 0,
						"type": "constant int",
						"source": "box: [param sw5 0] => sw5"
					}
				],
				"attributes": {
					
				},
				"type": "control t_sample",
				"typename": "Param",
				"source": "box: [param sw5 0] => sw5"
			},
			{
				"class": "Declaration",
				"id": "node_11312",
				"name": "knob6_res",
				"inputs": [
					{
						"class": "Constant",
						"id": "node_11313",
						"value": "0",
						"eval": 0,
						"type": "constant int",
						"source": "box: [param knob6_res 0] => knob6_res"
					}
				],
				"attributes": {
					
				},
				"type": "control t_sample",
				"typename": "Param",
				"source": "box: [param knob6_res 0] => knob6_res"
			},
			{
				"class": "Declaration",
				"id": "node_11310",
				"name": "knob3_manual",
				"inputs": [
					{
						"class": "Constant",
						"id": "node_11311",
						"value": "0",
						"eval": 0,
						"type": "constant int",
						"source": "box: [param knob3_manual 0] => knob3_manual"
					}
				],
				"attributes": {
					
				},
				"type": "control t_sample",
				"typename": "Param",
				"source": "box: [param knob3_manual 0] => knob3_manual"
			},
			{
				"class": "Declaration",
				"id": "node_11308",
				"name": "knob5_rate",
				"inputs": [
					{
						"class": "Constant",
						"id": "node_11309",
						"value": "0",
						"eval": 0,
						"type": "constant int",
						"source": "box: [param knob5_rate 0] => knob5_rate"
					}
				],
				"attributes": {
					
				},
				"type": "control t_sample",
				"typename": "Param",
				"source": "box: [param knob5_rate 0] => knob5_rate"
			},
			{
				"class": "Declaration",
				"id": "node_11306",
				"name": "knob4_depth",
				"inputs": [
					{
						"class": "Constant",
						"id": "node_11307",
						"value": "0",
						"eval": 0,
						"type": "constant int",
						"source": "box: [param knob4_depth 0] => knob4_depth"
					}
				],
				"attributes": {
					
				},
				"type": "control t_sample",
				"typename": "Param",
				"source": "box: [param knob4_depth 0] => knob4_depth"
			},
			{
				"class": "Declaration",
				"id": "node_11304",
				"name": "sw1",
				"inputs": [
					{
						"class": "Constant",
						"id": "node_11305",
						"value": "0",
						"eval": 0,
						"type": "constant int",
						"source": "box: [param sw1 0] => sw1"
					}
				],
				"attributes": {
					
				},
				"type": "control t_sample",
				"typename": "Param",
				"source": "box: [param sw1 0] => sw1"
			},
			{
				"class": "Declaration",
				"id": "node_11302",
				"name": "history_467",
				"inputs": [
					{
						"class": "Constant",
						"id": "node_11303",
						"value": "0",
						"eval": 0,
						"type": "constant int",
						"source": "box: [history history_467 0 $in1] => history_467"
					}
				],
				"attributes": {
					
				},
				"type": "signal t_sample",
				"typename": "History",
				"source": "source: [gen $in1 @file swtoggle] => gen_470 parent: box: [history history_467 0 $in1] => history_467"
			},
			{
				"class": "Statement",
				"id": "node_11340",
				"inputs": [
					{
						"class": "Expression",
						"id": "node_11341",
						"operator": "sah",
						"inputs": [
							{
								"class": "Variable",
								"id": "node_11342",
								"name": "history_467",
								"type": "signal t_sample",
								"source": "box: [sah $in1 $in2 $in3] => sah_468"
							},
							{
								"class": "Variable",
								"id": "node_11343",
								"name": "sw1",
								"type": "control t_sample",
								"source": "box: [sah $in1 $in2 $in3] => sah_468"
							},
							{
								"class": "Constant",
								"id": "node_11344",
								"value": "0",
								"eval": 0,
								"type": "constant int",
								"source": "box: [sah $in1 $in2 $in3] => sah_468"
							}
						],
						"attributes": {
							
						},
						"type": "signal t_sample",
						"source": "box: [sah $in1 $in2 $in3] => sah_468"
					}
				],
				"outputs": [
					{
						"class": "Variable",
						"id": "node_11345",
						"name": "sah_468",
						"type": "signal t_sample",
						"source": "box: [sah $in1 $in2 $in3] => sah_468"
					}
				],
				"source": "source: [gen $in1 @file swtoggle] => gen_470 parent: box: [sah $in1 $in2 $in3] => sah_468"
			},
			{
				"class": "Statement",
				"id": "node_11346",
				"inputs": [
					{
						"class": "Variable",
						"id": "node_11347",
						"name": "sah_468",
						"type": "signal t_sample",
						"source": "box: [out 1 $in1] => "
					}
				],
				"outputs": [
					{
						"class": "Variable",
						"id": "node_11348",
						"name": "gen_470",
						"type": "signal t_sample",
						"source": "box: [out 1 $in1] => "
					}
				],
				"source": "source: [gen $in1 @file swtoggle] => gen_470 parent: box: [out 1 $in1] => "
			},
			{
				"class": "Statement",
				"id": "node_11349",
				"inputs": [
					{
						"class": "Expression",
						"id": "node_11350",
						"operator": "sub",
						"inputs": [
							{
								"class": "Constant",
								"id": "node_11351",
								"value": "1",
								"eval": 1,
								"type": "constant int",
								"source": "box: [rsub $in1 1] => rsub_466"
							},
							{
								"class": "Variable",
								"id": "node_11352",
								"name": "sah_468",
								"type": "signal t_sample",
								"source": "box: [rsub $in1 1] => rsub_466"
							}
						],
						"attributes": {
							
						},
						"type": "signal t_sample",
						"source": "box: [rsub $in1 1] => rsub_466"
					}
				],
				"outputs": [
					{
						"class": "Variable",
						"id": "node_11353",
						"name": "rsub_466",
						"type": "signal t_sample",
						"source": "box: [rsub $in1 1] => rsub_466"
					}
				],
				"source": "source: [gen $in1 @file swtoggle] => gen_470 parent: box: [rsub $in1 1] => rsub_466"
			},
			{
				"class": "Statement",
				"id": "node_11354",
				"inputs": [
					{
						"class": "Expression",
						"id": "node_11355",
						"operator": "fixdenorm",
						"inputs": [
							{
								"class": "Variable",
								"id": "node_11356",
								"name": "rsub_466",
								"type": "signal t_sample",
								"source": "box: [history history_467 0 $in1] => history_467"
							}
						],
						"attributes": {
							
						},
						"type": "signal t_sample",
						"source": "box: [history history_467 0 $in1] => history_467"
					}
				],
				"outputs": [
					{
						"class": "Variable",
						"id": "node_11357",
						"name": "history_467_next_469",
						"type": "signal t_sample",
						"source": "box: [history history_467 0 $in1] => history_467"
					}
				],
				"source": "source: [gen $in1 @file swtoggle] => gen_470 parent: box: [history history_467 0 $in1] => history_467"
			},
			{
				"class": "Statement",
				"id": "node_11358",
				"inputs": [
					{
						"class": "Variable",
						"id": "node_11359",
						"name": "gen_470",
						"type": "signal t_sample",
						"source": "box: [out 3 $in1] => "
					}
				],
				"outputs": [
					{
						"class": "Variable",
						"id": "node_11360",
						"name": "out3",
						"type": "signal t_sample",
						"source": "box: [out 3 $in1] => "
					}
				],
				"source": "box: [out 3 $in1] => "
			},
			{
				"class": "Statement",
				"id": "node_11365",
				"inputs": [
					{
						"class": "Constant",
						"id": "node_11825",
						"value": 0,
						"eval": 0,
						"type": "constant int",
						"source": "box: [out 5 $in1] => "
					}
				],
				"outputs": [
					{
						"class": "Variable",
						"id": "node_11367",
						"name": "out5",
						"type": "signal t_sample",
						"source": "box: [out 5 $in1] => "
					}
				],
				"source": "box: [out 5 $in1] => "
			},
			{
				"class": "Statement",
				"id": "node_11368",
				"inputs": [
					{
						"class": "Constant",
						"id": "node_11826",
						"value": 0,
						"eval": 0,
						"type": "constant int",
						"source": "box: [out 4 $in1] => "
					}
				],
				"outputs": [
					{
						"class": "Variable",
						"id": "node_11370",
						"name": "out4",
						"type": "signal t_sample",
						"source": "box: [out 4 $in1] => "
					}
				],
				"source": "box: [out 4 $in1] => "
			},
			{
				"class": "Statement",
				"id": "node_11371",
				"inputs": [
					{
						"class": "Constant",
						"id": "node_11827",
						"value": 0,
						"eval": 0,
						"type": "constant int",
						"source": "box: [out 6 $in1] => "
					}
				],
				"outputs": [
					{
						"class": "Variable",
						"id": "node_11373",
						"name": "out6",
						"type": "signal t_sample",
						"source": "box: [out 6 $in1] => "
					}
				],
				"source": "box: [out 6 $in1] => "
			},
			{
				"class": "Statement",
				"id": "node_11670",
				"inputs": [
					{
						"class": "Expression",
						"id": "node_11671",
						"operator": "add",
						"inputs": [
							{
								"class": "Variable",
								"id": "node_11680",
								"name": "history_448",
								"type": "signal t_sample",
								"source": "code: 1:9 -> 1:9 [mix $in1 $in2 $in3] => mix_447"
							},
							{
								"class": "Expression",
								"id": "node_11673",
								"operator": "mul",
								"inputs": [
									{
										"class": "Constant",
										"id": "node_11829",
										"value": 0.003926980723806,
										"eval": 0.003926980723806,
										"type": "constant t_sample",
										"source": "code: 1:13 -> 1:13 [mix $in1 $in2 $in3] => mix_447"
									},
									{
										"class": "Expression",
										"id": "node_11675",
										"operator": "sub",
										"inputs": [
											{
												"class": "Variable",
												"id": "node_11682",
												"name": "knob5_rate",
												"type": "control t_sample",
												"source": "code: 1:18 -> 1:18 [mix $in1 $in2 $in3] => mix_447"
											},
											{
												"class": "Variable",
												"id": "node_11683",
												"name": "history_448",
												"type": "signal t_sample",
												"source": "code: 1:22 -> 1:22 [mix $in1 $in2 $in3] => mix_447"
											}
										],
										"attributes": {
											
										},
										"type": "signal t_sample",
										"source": "code: 1:18 -> 1:25 [mix $in1 $in2 $in3] => mix_447"
									}
								],
								"attributes": {
									
								},
								"type": "signal t_sample",
								"source": "code: 1:13 -> 1:25 [mix $in1 $in2 $in3] => mix_447"
							}
						],
						"attributes": {
							
						},
						"type": "signal t_sample",
						"source": "code: 1:9 -> 1:25 [mix $in1 $in2 $in3] => mix_447"
					}
				],
				"outputs": [
					{
						"class": "Variable",
						"id": "node_11679",
						"name": "mix_530",
						"type": "signal t_sample",
						"source": "code: 1:2 -> 1:2 [mix $in1 $in2 $in3] => mix_447"
					}
				],
				"source": "code: 1:2 -> 1:25 [mix $in1 $in2 $in3] => mix_447"
			},
			{
				"class": "Statement",
				"id": "node_11378",
				"inputs": [
					{
						"class": "Variable",
						"id": "node_11684",
						"name": "mix_530",
						"type": "signal t_sample",
						"source": "box: [mix $in1 $in2 $in3] => mix_447"
					}
				],
				"outputs": [
					{
						"class": "Variable",
						"id": "node_11383",
						"name": "mix_447",
						"type": "signal t_sample",
						"source": "box: [mix $in1 $in2 $in3] => mix_447"
					}
				],
				"source": "source: [gen $in1 @file oopsy.ctrl.smooth3] => gen_454 parent: box: [mix $in1 $in2 $in3] => mix_447"
			},
			{
				"class": "Statement",
				"id": "node_11687",
				"inputs": [
					{
						"class": "Expression",
						"id": "node_11688",
						"operator": "add",
						"inputs": [
							{
								"class": "Variable",
								"id": "node_11697",
								"name": "history_446",
								"type": "signal t_sample",
								"source": "code: 1:9 -> 1:9 [mix $in1 $in2 $in3] => mix_445"
							},
							{
								"class": "Expression",
								"id": "node_11690",
								"operator": "mul",
								"inputs": [
									{
										"class": "Constant",
										"id": "node_11830",
										"value": 0.003926980723806,
										"eval": 0.003926980723806,
										"type": "constant t_sample",
										"source": "code: 1:13 -> 1:13 [mix $in1 $in2 $in3] => mix_445"
									},
									{
										"class": "Expression",
										"id": "node_11692",
										"operator": "sub",
										"inputs": [
											{
												"class": "Variable",
												"id": "node_11699",
												"name": "mix_447",
												"type": "signal t_sample",
												"source": "code: 1:18 -> 1:18 [mix $in1 $in2 $in3] => mix_445"
											},
											{
												"class": "Variable",
												"id": "node_11700",
												"name": "history_446",
												"type": "signal t_sample",
												"source": "code: 1:22 -> 1:22 [mix $in1 $in2 $in3] => mix_445"
											}
										],
										"attributes": {
											
										},
										"type": "signal t_sample",
										"source": "code: 1:18 -> 1:25 [mix $in1 $in2 $in3] => mix_445"
									}
								],
								"attributes": {
									
								},
								"type": "signal t_sample",
								"source": "code: 1:13 -> 1:25 [mix $in1 $in2 $in3] => mix_445"
							}
						],
						"attributes": {
							
						},
						"type": "signal t_sample",
						"source": "code: 1:9 -> 1:25 [mix $in1 $in2 $in3] => mix_445"
					}
				],
				"outputs": [
					{
						"class": "Variable",
						"id": "node_11696",
						"name": "mix_531",
						"type": "signal t_sample",
						"source": "code: 1:2 -> 1:2 [mix $in1 $in2 $in3] => mix_445"
					}
				],
				"source": "code: 1:2 -> 1:25 [mix $in1 $in2 $in3] => mix_445"
			},
			{
				"class": "Statement",
				"id": "node_11384",
				"inputs": [
					{
						"class": "Variable",
						"id": "node_11701",
						"name": "mix_531",
						"type": "signal t_sample",
						"source": "box: [mix $in1 $in2 $in3] => mix_445"
					}
				],
				"outputs": [
					{
						"class": "Variable",
						"id": "node_11389",
						"name": "mix_445",
						"type": "signal t_sample",
						"source": "box: [mix $in1 $in2 $in3] => mix_445"
					}
				],
				"source": "source: [gen $in1 @file oopsy.ctrl.smooth3] => gen_454 parent: box: [mix $in1 $in2 $in3] => mix_445"
			},
			{
				"class": "Statement",
				"id": "node_11704",
				"inputs": [
					{
						"class": "Expression",
						"id": "node_11705",
						"operator": "add",
						"inputs": [
							{
								"class": "Variable",
								"id": "node_11714",
								"name": "history_444",
								"type": "signal t_sample",
								"source": "code: 1:9 -> 1:9 [mix $in1 $in2 $in3] => mix_443"
							},
							{
								"class": "Expression",
								"id": "node_11707",
								"operator": "mul",
								"inputs": [
									{
										"class": "Constant",
										"id": "node_11831",
										"value": 0.003926980723806,
										"eval": 0.003926980723806,
										"type": "constant t_sample",
										"source": "code: 1:13 -> 1:13 [mix $in1 $in2 $in3] => mix_443"
									},
									{
										"class": "Expression",
										"id": "node_11709",
										"operator": "sub",
										"inputs": [
											{
												"class": "Variable",
												"id": "node_11716",
												"name": "mix_445",
												"type": "signal t_sample",
												"source": "code: 1:18 -> 1:18 [mix $in1 $in2 $in3] => mix_443"
											},
											{
												"class": "Variable",
												"id": "node_11717",
												"name": "history_444",
												"type": "signal t_sample",
												"source": "code: 1:22 -> 1:22 [mix $in1 $in2 $in3] => mix_443"
											}
										],
										"attributes": {
											
										},
										"type": "signal t_sample",
										"source": "code: 1:18 -> 1:25 [mix $in1 $in2 $in3] => mix_443"
									}
								],
								"attributes": {
									
								},
								"type": "signal t_sample",
								"source": "code: 1:13 -> 1:25 [mix $in1 $in2 $in3] => mix_443"
							}
						],
						"attributes": {
							
						},
						"type": "signal t_sample",
						"source": "code: 1:9 -> 1:25 [mix $in1 $in2 $in3] => mix_443"
					}
				],
				"outputs": [
					{
						"class": "Variable",
						"id": "node_11713",
						"name": "mix_532",
						"type": "signal t_sample",
						"source": "code: 1:2 -> 1:2 [mix $in1 $in2 $in3] => mix_443"
					}
				],
				"source": "code: 1:2 -> 1:25 [mix $in1 $in2 $in3] => mix_443"
			},
			{
				"class": "Statement",
				"id": "node_11390",
				"inputs": [
					{
						"class": "Variable",
						"id": "node_11718",
						"name": "mix_532",
						"type": "signal t_sample",
						"source": "box: [mix $in1 $in2 $in3] => mix_443"
					}
				],
				"outputs": [
					{
						"class": "Variable",
						"id": "node_11395",
						"name": "mix_443",
						"type": "signal t_sample",
						"source": "box: [mix $in1 $in2 $in3] => mix_443"
					}
				],
				"source": "source: [gen $in1 @file oopsy.ctrl.smooth3] => gen_454 parent: box: [mix $in1 $in2 $in3] => mix_443"
			},
			{
				"class": "Statement",
				"id": "node_11396",
				"inputs": [
					{
						"class": "Variable",
						"id": "node_11397",
						"name": "mix_443",
						"type": "signal t_sample",
						"source": "box: [out 1 $in1] => "
					}
				],
				"outputs": [
					{
						"class": "Variable",
						"id": "node_11398",
						"name": "gen_454",
						"type": "signal t_sample",
						"source": "box: [out 1 $in1] => "
					}
				],
				"source": "source: [gen $in1 @file oopsy.ctrl.smooth3] => gen_454 parent: box: [out 1 $in1] => "
			},
			{
				"class": "Statement",
				"id": "node_11399",
				"inputs": [
					{
						"class": "Expression",
						"id": "node_11400",
						"operator": "fixdenorm",
						"inputs": [
							{
								"class": "Variable",
								"id": "node_11401",
								"name": "mix_447",
								"type": "signal t_sample",
								"source": "box: [history history_448 0 $in1] => history_448"
							}
						],
						"attributes": {
							
						},
						"type": "signal t_sample",
						"source": "box: [history history_448 0 $in1] => history_448"
					}
				],
				"outputs": [
					{
						"class": "Variable",
						"id": "node_11402",
						"name": "history_448_next_450",
						"type": "signal t_sample",
						"source": "box: [history history_448 0 $in1] => history_448"
					}
				],
				"source": "source: [gen $in1 @file oopsy.ctrl.smooth3] => gen_454 parent: box: [history history_448 0 $in1] => history_448"
			},
			{
				"class": "Statement",
				"id": "node_11403",
				"inputs": [
					{
						"class": "Expression",
						"id": "node_11404",
						"operator": "fixdenorm",
						"inputs": [
							{
								"class": "Variable",
								"id": "node_11405",
								"name": "mix_445",
								"type": "signal t_sample",
								"source": "box: [history history_446 0 $in1] => history_446"
							}
						],
						"attributes": {
							
						},
						"type": "signal t_sample",
						"source": "box: [history history_446 0 $in1] => history_446"
					}
				],
				"outputs": [
					{
						"class": "Variable",
						"id": "node_11406",
						"name": "history_446_next_451",
						"type": "signal t_sample",
						"source": "box: [history history_446 0 $in1] => history_446"
					}
				],
				"source": "source: [gen $in1 @file oopsy.ctrl.smooth3] => gen_454 parent: box: [history history_446 0 $in1] => history_446"
			},
			{
				"class": "Statement",
				"id": "node_11407",
				"inputs": [
					{
						"class": "Expression",
						"id": "node_11408",
						"operator": "fixdenorm",
						"inputs": [
							{
								"class": "Variable",
								"id": "node_11409",
								"name": "mix_443",
								"type": "signal t_sample",
								"source": "box: [history history_444 0 $in1] => history_444"
							}
						],
						"attributes": {
							
						},
						"type": "signal t_sample",
						"source": "box: [history history_444 0 $in1] => history_444"
					}
				],
				"outputs": [
					{
						"class": "Variable",
						"id": "node_11410",
						"name": "history_444_next_452",
						"type": "signal t_sample",
						"source": "box: [history history_444 0 $in1] => history_444"
					}
				],
				"source": "source: [gen $in1 @file oopsy.ctrl.smooth3] => gen_454 parent: box: [history history_444 0 $in1] => history_444"
			},
			{
				"class": "Statement",
				"id": "node_11411",
				"inputs": [
					{
						"class": "Expression",
						"id": "node_11412",
						"operator": "sub",
						"inputs": [
							{
								"class": "Constant",
								"id": "node_11413",
								"value": 1,
								"eval": 1,
								"type": "constant int",
								"source": "code: 1:1 -> 1:1 [expr $in1] => expr_492"
							},
							{
								"class": "Expression",
								"id": "node_11414",
								"operator": "sqrt",
								"inputs": [
									{
										"class": "Expression",
										"id": "node_11415",
										"operator": "sqrt",
										"inputs": [
											{
												"class": "Expression",
												"id": "node_11416",
												"operator": "sub",
												"inputs": [
													{
														"class": "Constant",
														"id": "node_11417",
														"value": 1,
														"eval": 1,
														"type": "constant int",
														"source": "code: 1:16 -> 1:16 [expr $in1] => expr_492"
													},
													{
														"class": "Variable",
														"id": "node_11418",
														"name": "gen_454",
														"type": "signal t_sample",
														"source": "code: 1:20 -> 1:20 [expr $in1] => expr_492"
													}
												],
												"attributes": {
													
												},
												"type": "signal t_sample",
												"source": "code: 1:16 -> 1:23 [expr $in1] => expr_492"
											}
										],
										"attributes": {
											
										},
										"type": "signal t_sample",
										"source": "code: 1:11 -> 1:23 [expr $in1] => expr_492"
									}
								],
								"attributes": {
									
								},
								"type": "signal t_sample",
								"source": "code: 1:6 -> 1:23 [expr $in1] => expr_492"
							}
						],
						"attributes": {
							
						},
						"type": "signal t_sample",
						"source": "code: 1:1 -> 1:23 [expr $in1] => expr_492"
					}
				],
				"outputs": [
					{
						"class": "Variable",
						"id": "node_11419",
						"name": "expr_492",
						"type": "signal t_sample",
						"source": "code: 1:1 -> 1:23 [expr $in1] => expr_492"
					}
				],
				"source": "code: 1:1 -> 1:23 [expr $in1] => expr_492"
			},
			{
				"class": "Statement",
				"id": "node_11721",
				"inputs": [
					{
						"class": "Expression",
						"id": "node_11722",
						"operator": "add",
						"inputs": [
							{
								"class": "Variable",
								"id": "node_11731",
								"name": "history_503",
								"type": "signal t_sample",
								"source": "code: 1:9 -> 1:9 [mix $in1 $in2 $in3] => mix_447"
							},
							{
								"class": "Expression",
								"id": "node_11724",
								"operator": "mul",
								"inputs": [
									{
										"class": "Constant",
										"id": "node_11833",
										"value": 0.003926980723806,
										"eval": 0.003926980723806,
										"type": "constant t_sample",
										"source": "code: 1:13 -> 1:13 [mix $in1 $in2 $in3] => mix_447"
									},
									{
										"class": "Expression",
										"id": "node_11726",
										"operator": "sub",
										"inputs": [
											{
												"class": "Variable",
												"id": "node_11733",
												"name": "knob3_manual",
												"type": "control t_sample",
												"source": "code: 1:18 -> 1:18 [mix $in1 $in2 $in3] => mix_447"
											},
											{
												"class": "Variable",
												"id": "node_11734",
												"name": "history_503",
												"type": "signal t_sample",
												"source": "code: 1:22 -> 1:22 [mix $in1 $in2 $in3] => mix_447"
											}
										],
										"attributes": {
											
										},
										"type": "signal t_sample",
										"source": "code: 1:18 -> 1:25 [mix $in1 $in2 $in3] => mix_447"
									}
								],
								"attributes": {
									
								},
								"type": "signal t_sample",
								"source": "code: 1:13 -> 1:25 [mix $in1 $in2 $in3] => mix_447"
							}
						],
						"attributes": {
							
						},
						"type": "signal t_sample",
						"source": "code: 1:9 -> 1:25 [mix $in1 $in2 $in3] => mix_447"
					}
				],
				"outputs": [
					{
						"class": "Variable",
						"id": "node_11730",
						"name": "mix_533",
						"type": "signal t_sample",
						"source": "code: 1:2 -> 1:2 [mix $in1 $in2 $in3] => mix_447"
					}
				],
				"source": "code: 1:2 -> 1:25 [mix $in1 $in2 $in3] => mix_447"
			},
			{
				"class": "Statement",
				"id": "node_11424",
				"inputs": [
					{
						"class": "Variable",
						"id": "node_11735",
						"name": "mix_533",
						"type": "signal t_sample",
						"source": "box: [mix $in1 $in2 $in3] => mix_447"
					}
				],
				"outputs": [
					{
						"class": "Variable",
						"id": "node_11429",
						"name": "mix_494",
						"type": "signal t_sample",
						"source": "box: [mix $in1 $in2 $in3] => mix_447"
					}
				],
				"source": "source: [gen $in1 @file oopsy.ctrl.smooth3] => gen_455 parent: box: [mix $in1 $in2 $in3] => mix_447"
			},
			{
				"class": "Statement",
				"id": "node_11738",
				"inputs": [
					{
						"class": "Expression",
						"id": "node_11739",
						"operator": "add",
						"inputs": [
							{
								"class": "Variable",
								"id": "node_11748",
								"name": "history_505",
								"type": "signal t_sample",
								"source": "code: 1:9 -> 1:9 [mix $in1 $in2 $in3] => mix_445"
							},
							{
								"class": "Expression",
								"id": "node_11741",
								"operator": "mul",
								"inputs": [
									{
										"class": "Constant",
										"id": "node_11834",
										"value": 0.003926980723806,
										"eval": 0.003926980723806,
										"type": "constant t_sample",
										"source": "code: 1:13 -> 1:13 [mix $in1 $in2 $in3] => mix_445"
									},
									{
										"class": "Expression",
										"id": "node_11743",
										"operator": "sub",
										"inputs": [
											{
												"class": "Variable",
												"id": "node_11750",
												"name": "mix_494",
												"type": "signal t_sample",
												"source": "code: 1:18 -> 1:18 [mix $in1 $in2 $in3] => mix_445"
											},
											{
												"class": "Variable",
												"id": "node_11751",
												"name": "history_505",
												"type": "signal t_sample",
												"source": "code: 1:22 -> 1:22 [mix $in1 $in2 $in3] => mix_445"
											}
										],
										"attributes": {
											
										},
										"type": "signal t_sample",
										"source": "code: 1:18 -> 1:25 [mix $in1 $in2 $in3] => mix_445"
									}
								],
								"attributes": {
									
								},
								"type": "signal t_sample",
								"source": "code: 1:13 -> 1:25 [mix $in1 $in2 $in3] => mix_445"
							}
						],
						"attributes": {
							
						},
						"type": "signal t_sample",
						"source": "code: 1:9 -> 1:25 [mix $in1 $in2 $in3] => mix_445"
					}
				],
				"outputs": [
					{
						"class": "Variable",
						"id": "node_11747",
						"name": "mix_534",
						"type": "signal t_sample",
						"source": "code: 1:2 -> 1:2 [mix $in1 $in2 $in3] => mix_445"
					}
				],
				"source": "code: 1:2 -> 1:25 [mix $in1 $in2 $in3] => mix_445"
			},
			{
				"class": "Statement",
				"id": "node_11430",
				"inputs": [
					{
						"class": "Variable",
						"id": "node_11752",
						"name": "mix_534",
						"type": "signal t_sample",
						"source": "box: [mix $in1 $in2 $in3] => mix_445"
					}
				],
				"outputs": [
					{
						"class": "Variable",
						"id": "node_11435",
						"name": "mix_493",
						"type": "signal t_sample",
						"source": "box: [mix $in1 $in2 $in3] => mix_445"
					}
				],
				"source": "source: [gen $in1 @file oopsy.ctrl.smooth3] => gen_455 parent: box: [mix $in1 $in2 $in3] => mix_445"
			},
			{
				"class": "Statement",
				"id": "node_11755",
				"inputs": [
					{
						"class": "Expression",
						"id": "node_11756",
						"operator": "add",
						"inputs": [
							{
								"class": "Variable",
								"id": "node_11765",
								"name": "history_504",
								"type": "signal t_sample",
								"source": "code: 1:9 -> 1:9 [mix $in1 $in2 $in3] => mix_443"
							},
							{
								"class": "Expression",
								"id": "node_11758",
								"operator": "mul",
								"inputs": [
									{
										"class": "Constant",
										"id": "node_11835",
										"value": 0.003926980723806,
										"eval": 0.003926980723806,
										"type": "constant t_sample",
										"source": "code: 1:13 -> 1:13 [mix $in1 $in2 $in3] => mix_443"
									},
									{
										"class": "Expression",
										"id": "node_11760",
										"operator": "sub",
										"inputs": [
											{
												"class": "Variable",
												"id": "node_11767",
												"name": "mix_493",
												"type": "signal t_sample",
												"source": "code: 1:18 -> 1:18 [mix $in1 $in2 $in3] => mix_443"
											},
											{
												"class": "Variable",
												"id": "node_11768",
												"name": "history_504",
												"type": "signal t_sample",
												"source": "code: 1:22 -> 1:22 [mix $in1 $in2 $in3] => mix_443"
											}
										],
										"attributes": {
											
										},
										"type": "signal t_sample",
										"source": "code: 1:18 -> 1:25 [mix $in1 $in2 $in3] => mix_443"
									}
								],
								"attributes": {
									
								},
								"type": "signal t_sample",
								"source": "code: 1:13 -> 1:25 [mix $in1 $in2 $in3] => mix_443"
							}
						],
						"attributes": {
							
						},
						"type": "signal t_sample",
						"source": "code: 1:9 -> 1:25 [mix $in1 $in2 $in3] => mix_443"
					}
				],
				"outputs": [
					{
						"class": "Variable",
						"id": "node_11764",
						"name": "mix_535",
						"type": "signal t_sample",
						"source": "code: 1:2 -> 1:2 [mix $in1 $in2 $in3] => mix_443"
					}
				],
				"source": "code: 1:2 -> 1:25 [mix $in1 $in2 $in3] => mix_443"
			},
			{
				"class": "Statement",
				"id": "node_11436",
				"inputs": [
					{
						"class": "Variable",
						"id": "node_11769",
						"name": "mix_535",
						"type": "signal t_sample",
						"source": "box: [mix $in1 $in2 $in3] => mix_443"
					}
				],
				"outputs": [
					{
						"class": "Variable",
						"id": "node_11441",
						"name": "mix_500",
						"type": "signal t_sample",
						"source": "box: [mix $in1 $in2 $in3] => mix_443"
					}
				],
				"source": "source: [gen $in1 @file oopsy.ctrl.smooth3] => gen_455 parent: box: [mix $in1 $in2 $in3] => mix_443"
			},
			{
				"class": "Statement",
				"id": "node_11442",
				"inputs": [
					{
						"class": "Variable",
						"id": "node_11443",
						"name": "mix_500",
						"type": "signal t_sample",
						"source": "box: [out 1 $in1] => "
					}
				],
				"outputs": [
					{
						"class": "Variable",
						"id": "node_11444",
						"name": "gen_455",
						"type": "signal t_sample",
						"source": "box: [out 1 $in1] => "
					}
				],
				"source": "source: [gen $in1 @file oopsy.ctrl.smooth3] => gen_455 parent: box: [out 1 $in1] => "
			},
			{
				"class": "Statement",
				"id": "node_11445",
				"inputs": [
					{
						"class": "Expression",
						"id": "node_11446",
						"operator": "fixdenorm",
						"inputs": [
							{
								"class": "Variable",
								"id": "node_11447",
								"name": "mix_494",
								"type": "signal t_sample",
								"source": "box: [history history_448 0 $in1] => history_448"
							}
						],
						"attributes": {
							
						},
						"type": "signal t_sample",
						"source": "box: [history history_448 0 $in1] => history_448"
					}
				],
				"outputs": [
					{
						"class": "Variable",
						"id": "node_11448",
						"name": "history_448_next_499",
						"type": "signal t_sample",
						"source": "box: [history history_448 0 $in1] => history_448"
					}
				],
				"source": "source: [gen $in1 @file oopsy.ctrl.smooth3] => gen_455 parent: box: [history history_448 0 $in1] => history_448"
			},
			{
				"class": "Statement",
				"id": "node_11449",
				"inputs": [
					{
						"class": "Expression",
						"id": "node_11450",
						"operator": "fixdenorm",
						"inputs": [
							{
								"class": "Variable",
								"id": "node_11451",
								"name": "mix_493",
								"type": "signal t_sample",
								"source": "box: [history history_446 0 $in1] => history_446"
							}
						],
						"attributes": {
							
						},
						"type": "signal t_sample",
						"source": "box: [history history_446 0 $in1] => history_446"
					}
				],
				"outputs": [
					{
						"class": "Variable",
						"id": "node_11452",
						"name": "history_446_next_498",
						"type": "signal t_sample",
						"source": "box: [history history_446 0 $in1] => history_446"
					}
				],
				"source": "source: [gen $in1 @file oopsy.ctrl.smooth3] => gen_455 parent: box: [history history_446 0 $in1] => history_446"
			},
			{
				"class": "Statement",
				"id": "node_11453",
				"inputs": [
					{
						"class": "Expression",
						"id": "node_11454",
						"operator": "fixdenorm",
						"inputs": [
							{
								"class": "Variable",
								"id": "node_11455",
								"name": "mix_500",
								"type": "signal t_sample",
								"source": "box: [history history_444 0 $in1] => history_444"
							}
						],
						"attributes": {
							
						},
						"type": "signal t_sample",
						"source": "box: [history history_444 0 $in1] => history_444"
					}
				],
				"outputs": [
					{
						"class": "Variable",
						"id": "node_11456",
						"name": "history_444_next_497",
						"type": "signal t_sample",
						"source": "box: [history history_444 0 $in1] => history_444"
					}
				],
				"source": "source: [gen $in1 @file oopsy.ctrl.smooth3] => gen_455 parent: box: [history history_444 0 $in1] => history_444"
			},
			{
				"class": "Statement",
				"id": "node_11457",
				"inputs": [
					{
						"class": "Expression",
						"id": "node_11458",
						"operator": "sub",
						"inputs": [
							{
								"class": "Constant",
								"id": "node_11459",
								"value": 1,
								"eval": 1,
								"type": "constant int",
								"source": "code: 1:1 -> 1:1 [expr $in1] => expr_491"
							},
							{
								"class": "Expression",
								"id": "node_11460",
								"operator": "sqrt",
								"inputs": [
									{
										"class": "Expression",
										"id": "node_11461",
										"operator": "sub",
										"inputs": [
											{
												"class": "Constant",
												"id": "node_11462",
												"value": 1,
												"eval": 1,
												"type": "constant int",
												"source": "code: 1:11 -> 1:11 [expr $in1] => expr_491"
											},
											{
												"class": "Variable",
												"id": "node_11463",
												"name": "gen_455",
												"type": "signal t_sample",
												"source": "code: 1:15 -> 1:15 [expr $in1] => expr_491"
											}
										],
										"attributes": {
											
										},
										"type": "signal t_sample",
										"source": "code: 1:11 -> 1:18 [expr $in1] => expr_491"
									}
								],
								"attributes": {
									
								},
								"type": "signal t_sample",
								"source": "code: 1:6 -> 1:18 [expr $in1] => expr_491"
							}
						],
						"attributes": {
							
						},
						"type": "signal t_sample",
						"source": "code: 1:1 -> 1:18 [expr $in1] => expr_491"
					}
				],
				"outputs": [
					{
						"class": "Variable",
						"id": "node_11464",
						"name": "expr_491",
						"type": "signal t_sample",
						"source": "code: 1:1 -> 1:18 [expr $in1] => expr_491"
					}
				],
				"source": "code: 1:1 -> 1:18 [expr $in1] => expr_491"
			},
			{
				"class": "Statement",
				"id": "node_11465",
				"inputs": [
					{
						"class": "Expression",
						"id": "node_11466",
						"operator": "add",
						"inputs": [
							{
								"class": "Variable",
								"id": "node_11467",
								"name": "gen_470",
								"type": "signal t_sample",
								"source": "box: [add $in1 1] => add_473"
							},
							{
								"class": "Constant",
								"id": "node_11468",
								"value": "1",
								"eval": 1,
								"type": "constant int",
								"source": "box: [add $in1 1] => add_473"
							}
						],
						"attributes": {
							
						},
						"type": "signal t_sample",
						"source": "box: [add $in1 1] => add_473"
					}
				],
				"outputs": [
					{
						"class": "Variable",
						"id": "node_11469",
						"name": "add_473",
						"type": "signal t_sample",
						"source": "box: [add $in1 1] => add_473"
					}
				],
				"source": "box: [add $in1 1] => add_473"
			},
			{
				"class": "Statement",
				"id": "node_11470",
				"inputs": [
					{
						"class": "Expression",
						"id": "node_11471",
						"operator": "gate",
						"inputs": [
							{
								"class": "Variable",
								"id": "node_11472",
								"name": "add_473",
								"type": "signal t_sample",
								"source": "box: [gate $in1 $in2 @choices 2] => gate_471,gate_472"
							},
							{
								"class": "Variable",
								"id": "node_11473",
								"name": "in1",
								"type": "signal t_sample",
								"source": "box: [gate $in1 $in2 @choices 2] => gate_471,gate_472"
							}
						],
						"attributes": {
							"choices": {
								"class": "Attribute",
								"id": "node_11474",
								"name": "choices",
								"value": {
									"class": "Constant",
									"id": "node_10548",
									"value": "2",
									"eval": 2,
									"type": "constant int",
									"source": "box: [gate $in1 $in2 @choices 2] => gate_471,gate_472"
								},
								"source": "box: [gate $in1 $in2 @choices 2] => gate_471,gate_472"
							}
						},
						"type": "signal t_sample",
						"source": "box: [gate $in1 $in2 @choices 2] => gate_471,gate_472"
					}
				],
				"outputs": [
					{
						"class": "Variable",
						"id": "node_11475",
						"name": "gate_471",
						"type": "signal t_sample",
						"source": "box: [gate $in1 $in2 @choices 2] => gate_471,gate_472"
					},
					{
						"class": "Variable",
						"id": "node_11476",
						"name": "gate_472",
						"type": "signal t_sample",
						"source": "box: [gate $in1 $in2 @choices 2] => gate_471,gate_472"
					}
				],
				"source": "box: [gate $in1 $in2 @choices 2] => gate_471,gate_472"
			},
			{
				"class": "Statement",
				"id": "node_11477",
				"inputs": [
					{
						"class": "Expression",
						"id": "node_11478",
						"operator": "mul",
						"inputs": [
							{
								"class": "Variable",
								"id": "node_11479",
								"name": "expr_491",
								"type": "signal t_sample",
								"source": "box: [mul $in1 1920] => mul_488"
							},
							{
								"class": "Constant",
								"id": "node_11480",
								"value": "1920",
								"eval": 1920,
								"type": "constant int",
								"source": "box: [mul $in1 1920] => mul_488"
							}
						],
						"attributes": {
							
						},
						"type": "signal t_sample",
						"source": "box: [mul $in1 1920] => mul_488"
					}
				],
				"outputs": [
					{
						"class": "Variable",
						"id": "node_11481",
						"name": "mul_488",
						"type": "signal t_sample",
						"source": "box: [mul $in1 1920] => mul_488"
					}
				],
				"source": "box: [mul $in1 1920] => mul_488"
			},
			{
				"class": "Statement",
				"id": "node_11482",
				"inputs": [
					{
						"class": "Expression",
						"id": "node_11483",
						"operator": "read",
						"inputs": [
							{
								"class": "Variable",
								"id": "node_11484",
								"name": "delay_463",
								"type": "init Delay",
								"source": "box: [delay 3840 $in1 $in2] => tap_464"
							},
							{
								"class": "Variable",
								"id": "node_11485",
								"name": "mul_488",
								"type": "signal t_sample",
								"source": "box: [delay 3840 $in1 $in2] => tap_464"
							}
						],
						"attributes": {
							
						},
						"type": "signal t_sample",
						"source": "box: [delay 3840 $in1 $in2] => tap_464"
					}
				],
				"outputs": [
					{
						"class": "Variable",
						"id": "node_11486",
						"name": "tap_464",
						"type": "signal t_sample",
						"source": "box: [delay 3840 $in1 $in2] => tap_464"
					}
				],
				"source": "box: [delay 3840 $in1 $in2] => tap_464"
			},
			{
				"class": "Statement",
				"id": "node_11487",
				"inputs": [
					{
						"class": "Expression",
						"id": "node_11488",
						"operator": "switch",
						"inputs": [
							{
								"class": "Variable",
								"id": "node_11489",
								"name": "sw5",
								"type": "control t_sample",
								"source": "box: [switch $in1 $in2 $in3] => switch_462"
							},
							{
								"class": "Variable",
								"id": "node_11490",
								"name": "tap_464",
								"type": "signal t_sample",
								"source": "box: [switch $in1 $in2 $in3] => switch_462"
							},
							{
								"class": "Variable",
								"id": "node_11491",
								"name": "gate_472",
								"type": "signal t_sample",
								"source": "box: [switch $in1 $in2 $in3] => switch_462"
							}
						],
						"attributes": {
							
						},
						"type": "signal t_sample",
						"source": "box: [switch $in1 $in2 $in3] => switch_462"
					}
				],
				"outputs": [
					{
						"class": "Variable",
						"id": "node_11492",
						"name": "switch_462",
						"type": "signal t_sample",
						"source": "box: [switch $in1 $in2 $in3] => switch_462"
					}
				],
				"source": "box: [switch $in1 $in2 $in3] => switch_462"
			},
			{
				"class": "Statement",
				"id": "node_11493",
				"inputs": [
					{
						"class": "Expression",
						"id": "node_11494",
						"operator": "sqrt",
						"inputs": [
							{
								"class": "Variable",
								"id": "node_11495",
								"name": "knob6_res",
								"type": "control t_sample",
								"source": "box: [sqrt $in1] => sqrt_465"
							}
						],
						"attributes": {
							
						},
						"type": "control t_sample",
						"source": "box: [sqrt $in1] => sqrt_465"
					}
				],
				"outputs": [
					{
						"class": "Variable",
						"id": "node_11496",
						"name": "sqrt_465",
						"type": "control t_sample",
						"source": "box: [sqrt $in1] => sqrt_465"
					}
				],
				"source": "box: [sqrt $in1] => sqrt_465"
			},
			{
				"class": "Statement",
				"id": "node_11497",
				"inputs": [
					{
						"class": "Expression",
						"id": "node_11498",
						"operator": "sqrt",
						"inputs": [
							{
								"class": "Variable",
								"id": "node_11499",
								"name": "sqrt_465",
								"type": "control t_sample",
								"source": "box: [sqrt $in1] => sqrt_474"
							}
						],
						"attributes": {
							
						},
						"type": "control t_sample",
						"source": "box: [sqrt $in1] => sqrt_474"
					}
				],
				"outputs": [
					{
						"class": "Variable",
						"id": "node_11500",
						"name": "sqrt_474",
						"type": "control t_sample",
						"source": "box: [sqrt $in1] => sqrt_474"
					}
				],
				"source": "box: [sqrt $in1] => sqrt_474"
			},
			{
				"class": "Statement",
				"id": "node_11501",
				"inputs": [
					{
						"class": "Expression",
						"id": "node_11502",
						"operator": "mul",
						"inputs": [
							{
								"class": "Variable",
								"id": "node_11503",
								"name": "sqrt_474",
								"type": "control t_sample",
								"source": "box: [mul $in1 0.99] => mul_486"
							},
							{
								"class": "Constant",
								"id": "node_11504",
								"value": "0.99",
								"eval": 0.99,
								"type": "constant t_sample",
								"source": "box: [mul $in1 0.99] => mul_486"
							}
						],
						"attributes": {
							
						},
						"type": "control t_sample",
						"source": "box: [mul $in1 0.99] => mul_486"
					}
				],
				"outputs": [
					{
						"class": "Variable",
						"id": "node_11505",
						"name": "mul_486",
						"type": "control t_sample",
						"source": "box: [mul $in1 0.99] => mul_486"
					}
				],
				"source": "box: [mul $in1 0.99] => mul_486"
			},
			{
				"class": "Statement",
				"id": "node_11506",
				"inputs": [
					{
						"class": "Expression",
						"id": "node_11507",
						"operator": "mul",
						"inputs": [
							{
								"class": "Variable",
								"id": "node_11508",
								"name": "expr_492",
								"type": "signal t_sample",
								"source": "box: [mul $in1 10.] => mul_477"
							},
							{
								"class": "Constant",
								"id": "node_11509",
								"value": "10.",
								"eval": 10,
								"type": "constant int",
								"source": "box: [mul $in1 10.] => mul_477"
							}
						],
						"attributes": {
							
						},
						"type": "signal t_sample",
						"source": "box: [mul $in1 10.] => mul_477"
					}
				],
				"outputs": [
					{
						"class": "Variable",
						"id": "node_11510",
						"name": "mul_477",
						"type": "signal t_sample",
						"source": "box: [mul $in1 10.] => mul_477"
					}
				],
				"source": "box: [mul $in1 10.] => mul_477"
			},
			{
				"class": "Statement",
				"id": "node_11511",
				"inputs": [
					{
						"class": "Expression",
						"id": "node_11512",
						"operator": "cycle",
						"inputs": [
							{
								"class": "Variable",
								"id": "node_11513",
								"name": "mul_477",
								"type": "signal t_sample",
								"source": "box: [cycle $in1] => cycle_478,cycleindex_479"
							}
						],
						"attributes": {
							
						},
						"type": "signal t_sample",
						"source": "box: [cycle $in1] => cycle_478,cycleindex_479"
					}
				],
				"outputs": [
					{
						"class": "Variable",
						"id": "node_11514",
						"name": "cycle_478",
						"type": "signal t_sample",
						"source": "box: [cycle $in1] => cycle_478,cycleindex_479"
					},
					{
						"class": "Variable",
						"id": "node_11515",
						"name": "cycleindex_479",
						"type": "signal t_sample",
						"source": "box: [cycle $in1] => cycle_478,cycleindex_479"
					}
				],
				"source": "box: [cycle $in1] => cycle_478,cycleindex_479"
			},
			{
				"class": "Statement",
				"id": "node_11772",
				"inputs": [
					{
						"class": "Expression",
						"id": "node_11773",
						"operator": "add",
						"inputs": [
							{
								"class": "Variable",
								"id": "node_11782",
								"name": "history_516",
								"type": "signal t_sample",
								"source": "code: 1:9 -> 1:9 [mix $in1 $in2 $in3] => mix_447"
							},
							{
								"class": "Expression",
								"id": "node_11775",
								"operator": "mul",
								"inputs": [
									{
										"class": "Constant",
										"id": "node_11837",
										"value": 0.003926980723806,
										"eval": 0.003926980723806,
										"type": "constant t_sample",
										"source": "code: 1:13 -> 1:13 [mix $in1 $in2 $in3] => mix_447"
									},
									{
										"class": "Expression",
										"id": "node_11777",
										"operator": "sub",
										"inputs": [
											{
												"class": "Variable",
												"id": "node_11784",
												"name": "knob4_depth",
												"type": "control t_sample",
												"source": "code: 1:18 -> 1:18 [mix $in1 $in2 $in3] => mix_447"
											},
											{
												"class": "Variable",
												"id": "node_11785",
												"name": "history_516",
												"type": "signal t_sample",
												"source": "code: 1:22 -> 1:22 [mix $in1 $in2 $in3] => mix_447"
											}
										],
										"attributes": {
											
										},
										"type": "signal t_sample",
										"source": "code: 1:18 -> 1:25 [mix $in1 $in2 $in3] => mix_447"
									}
								],
								"attributes": {
									
								},
								"type": "signal t_sample",
								"source": "code: 1:13 -> 1:25 [mix $in1 $in2 $in3] => mix_447"
							}
						],
						"attributes": {
							
						},
						"type": "signal t_sample",
						"source": "code: 1:9 -> 1:25 [mix $in1 $in2 $in3] => mix_447"
					}
				],
				"outputs": [
					{
						"class": "Variable",
						"id": "node_11781",
						"name": "mix_536",
						"type": "signal t_sample",
						"source": "code: 1:2 -> 1:2 [mix $in1 $in2 $in3] => mix_447"
					}
				],
				"source": "code: 1:2 -> 1:25 [mix $in1 $in2 $in3] => mix_447"
			},
			{
				"class": "Statement",
				"id": "node_11520",
				"inputs": [
					{
						"class": "Variable",
						"id": "node_11786",
						"name": "mix_536",
						"type": "signal t_sample",
						"source": "box: [mix $in1 $in2 $in3] => mix_447"
					}
				],
				"outputs": [
					{
						"class": "Variable",
						"id": "node_11525",
						"name": "mix_506",
						"type": "signal t_sample",
						"source": "box: [mix $in1 $in2 $in3] => mix_447"
					}
				],
				"source": "source: [gen $in1 @file oopsy.ctrl.smooth3] => gen_453 parent: box: [mix $in1 $in2 $in3] => mix_447"
			},
			{
				"class": "Statement",
				"id": "node_11789",
				"inputs": [
					{
						"class": "Expression",
						"id": "node_11790",
						"operator": "add",
						"inputs": [
							{
								"class": "Variable",
								"id": "node_11799",
								"name": "history_518",
								"type": "signal t_sample",
								"source": "code: 1:9 -> 1:9 [mix $in1 $in2 $in3] => mix_445"
							},
							{
								"class": "Expression",
								"id": "node_11792",
								"operator": "mul",
								"inputs": [
									{
										"class": "Constant",
										"id": "node_11838",
										"value": 0.003926980723806,
										"eval": 0.003926980723806,
										"type": "constant t_sample",
										"source": "code: 1:13 -> 1:13 [mix $in1 $in2 $in3] => mix_445"
									},
									{
										"class": "Expression",
										"id": "node_11794",
										"operator": "sub",
										"inputs": [
											{
												"class": "Variable",
												"id": "node_11801",
												"name": "mix_506",
												"type": "signal t_sample",
												"source": "code: 1:18 -> 1:18 [mix $in1 $in2 $in3] => mix_445"
											},
											{
												"class": "Variable",
												"id": "node_11802",
												"name": "history_518",
												"type": "signal t_sample",
												"source": "code: 1:22 -> 1:22 [mix $in1 $in2 $in3] => mix_445"
											}
										],
										"attributes": {
											
										},
										"type": "signal t_sample",
										"source": "code: 1:18 -> 1:25 [mix $in1 $in2 $in3] => mix_445"
									}
								],
								"attributes": {
									
								},
								"type": "signal t_sample",
								"source": "code: 1:13 -> 1:25 [mix $in1 $in2 $in3] => mix_445"
							}
						],
						"attributes": {
							
						},
						"type": "signal t_sample",
						"source": "code: 1:9 -> 1:25 [mix $in1 $in2 $in3] => mix_445"
					}
				],
				"outputs": [
					{
						"class": "Variable",
						"id": "node_11798",
						"name": "mix_537",
						"type": "signal t_sample",
						"source": "code: 1:2 -> 1:2 [mix $in1 $in2 $in3] => mix_445"
					}
				],
				"source": "code: 1:2 -> 1:25 [mix $in1 $in2 $in3] => mix_445"
			},
			{
				"class": "Statement",
				"id": "node_11526",
				"inputs": [
					{
						"class": "Variable",
						"id": "node_11803",
						"name": "mix_537",
						"type": "signal t_sample",
						"source": "box: [mix $in1 $in2 $in3] => mix_445"
					}
				],
				"outputs": [
					{
						"class": "Variable",
						"id": "node_11531",
						"name": "mix_510",
						"type": "signal t_sample",
						"source": "box: [mix $in1 $in2 $in3] => mix_445"
					}
				],
				"source": "source: [gen $in1 @file oopsy.ctrl.smooth3] => gen_453 parent: box: [mix $in1 $in2 $in3] => mix_445"
			},
			{
				"class": "Statement",
				"id": "node_11806",
				"inputs": [
					{
						"class": "Expression",
						"id": "node_11807",
						"operator": "add",
						"inputs": [
							{
								"class": "Variable",
								"id": "node_11816",
								"name": "history_517",
								"type": "signal t_sample",
								"source": "code: 1:9 -> 1:9 [mix $in1 $in2 $in3] => mix_443"
							},
							{
								"class": "Expression",
								"id": "node_11809",
								"operator": "mul",
								"inputs": [
									{
										"class": "Constant",
										"id": "node_11839",
										"value": 0.003926980723806,
										"eval": 0.003926980723806,
										"type": "constant t_sample",
										"source": "code: 1:13 -> 1:13 [mix $in1 $in2 $in3] => mix_443"
									},
									{
										"class": "Expression",
										"id": "node_11811",
										"operator": "sub",
										"inputs": [
											{
												"class": "Variable",
												"id": "node_11818",
												"name": "mix_510",
												"type": "signal t_sample",
												"source": "code: 1:18 -> 1:18 [mix $in1 $in2 $in3] => mix_443"
											},
											{
												"class": "Variable",
												"id": "node_11819",
												"name": "history_517",
												"type": "signal t_sample",
												"source": "code: 1:22 -> 1:22 [mix $in1 $in2 $in3] => mix_443"
											}
										],
										"attributes": {
											
										},
										"type": "signal t_sample",
										"source": "code: 1:18 -> 1:25 [mix $in1 $in2 $in3] => mix_443"
									}
								],
								"attributes": {
									
								},
								"type": "signal t_sample",
								"source": "code: 1:13 -> 1:25 [mix $in1 $in2 $in3] => mix_443"
							}
						],
						"attributes": {
							
						},
						"type": "signal t_sample",
						"source": "code: 1:9 -> 1:25 [mix $in1 $in2 $in3] => mix_443"
					}
				],
				"outputs": [
					{
						"class": "Variable",
						"id": "node_11815",
						"name": "mix_538",
						"type": "signal t_sample",
						"source": "code: 1:2 -> 1:2 [mix $in1 $in2 $in3] => mix_443"
					}
				],
				"source": "code: 1:2 -> 1:25 [mix $in1 $in2 $in3] => mix_443"
			},
			{
				"class": "Statement",
				"id": "node_11532",
				"inputs": [
					{
						"class": "Variable",
						"id": "node_11820",
						"name": "mix_538",
						"type": "signal t_sample",
						"source": "box: [mix $in1 $in2 $in3] => mix_443"
					}
				],
				"outputs": [
					{
						"class": "Variable",
						"id": "node_11537",
						"name": "mix_515",
						"type": "signal t_sample",
						"source": "box: [mix $in1 $in2 $in3] => mix_443"
					}
				],
				"source": "source: [gen $in1 @file oopsy.ctrl.smooth3] => gen_453 parent: box: [mix $in1 $in2 $in3] => mix_443"
			},
			{
				"class": "Statement",
				"id": "node_11538",
				"inputs": [
					{
						"class": "Variable",
						"id": "node_11539",
						"name": "mix_515",
						"type": "signal t_sample",
						"source": "box: [out 1 $in1] => "
					}
				],
				"outputs": [
					{
						"class": "Variable",
						"id": "node_11540",
						"name": "gen_453",
						"type": "signal t_sample",
						"source": "box: [out 1 $in1] => "
					}
				],
				"source": "source: [gen $in1 @file oopsy.ctrl.smooth3] => gen_453 parent: box: [out 1 $in1] => "
			},
			{
				"class": "Statement",
				"id": "node_11541",
				"inputs": [
					{
						"class": "Expression",
						"id": "node_11542",
						"operator": "fixdenorm",
						"inputs": [
							{
								"class": "Variable",
								"id": "node_11543",
								"name": "mix_506",
								"type": "signal t_sample",
								"source": "box: [history history_448 0 $in1] => history_448"
							}
						],
						"attributes": {
							
						},
						"type": "signal t_sample",
						"source": "box: [history history_448 0 $in1] => history_448"
					}
				],
				"outputs": [
					{
						"class": "Variable",
						"id": "node_11544",
						"name": "history_448_next_509",
						"type": "signal t_sample",
						"source": "box: [history history_448 0 $in1] => history_448"
					}
				],
				"source": "source: [gen $in1 @file oopsy.ctrl.smooth3] => gen_453 parent: box: [history history_448 0 $in1] => history_448"
			},
			{
				"class": "Statement",
				"id": "node_11545",
				"inputs": [
					{
						"class": "Expression",
						"id": "node_11546",
						"operator": "fixdenorm",
						"inputs": [
							{
								"class": "Variable",
								"id": "node_11547",
								"name": "mix_510",
								"type": "signal t_sample",
								"source": "box: [history history_446 0 $in1] => history_446"
							}
						],
						"attributes": {
							
						},
						"type": "signal t_sample",
						"source": "box: [history history_446 0 $in1] => history_446"
					}
				],
				"outputs": [
					{
						"class": "Variable",
						"id": "node_11548",
						"name": "history_446_next_512",
						"type": "signal t_sample",
						"source": "box: [history history_446 0 $in1] => history_446"
					}
				],
				"source": "source: [gen $in1 @file oopsy.ctrl.smooth3] => gen_453 parent: box: [history history_446 0 $in1] => history_446"
			},
			{
				"class": "Statement",
				"id": "node_11549",
				"inputs": [
					{
						"class": "Expression",
						"id": "node_11550",
						"operator": "fixdenorm",
						"inputs": [
							{
								"class": "Variable",
								"id": "node_11551",
								"name": "mix_515",
								"type": "signal t_sample",
								"source": "box: [history history_444 0 $in1] => history_444"
							}
						],
						"attributes": {
							
						},
						"type": "signal t_sample",
						"source": "box: [history history_444 0 $in1] => history_444"
					}
				],
				"outputs": [
					{
						"class": "Variable",
						"id": "node_11552",
						"name": "history_444_next_511",
						"type": "signal t_sample",
						"source": "box: [history history_444 0 $in1] => history_444"
					}
				],
				"source": "source: [gen $in1 @file oopsy.ctrl.smooth3] => gen_453 parent: box: [history history_444 0 $in1] => history_444"
			},
			{
				"class": "Statement",
				"id": "node_11553",
				"inputs": [
					{
						"class": "Expression",
						"id": "node_11554",
						"operator": "mul",
						"inputs": [
							{
								"class": "Variable",
								"id": "node_11555",
								"name": "gen_453",
								"type": "signal t_sample",
								"source": "box: [mul $in1 $in2] => mul_482"
							},
							{
								"class": "Variable",
								"id": "node_11556",
								"name": "mul_488",
								"type": "signal t_sample",
								"source": "box: [mul $in1 $in2] => mul_482"
							}
						],
						"attributes": {
							
						},
						"type": "signal t_sample",
						"source": "box: [mul $in1 $in2] => mul_482"
					}
				],
				"outputs": [
					{
						"class": "Variable",
						"id": "node_11557",
						"name": "mul_482",
						"type": "signal t_sample",
						"source": "box: [mul $in1 $in2] => mul_482"
					}
				],
				"source": "box: [mul $in1 $in2] => mul_482"
			},
			{
				"class": "Statement",
				"id": "node_11558",
				"inputs": [
					{
						"class": "Expression",
						"id": "node_11559",
						"operator": "mul",
						"inputs": [
							{
								"class": "Variable",
								"id": "node_11560",
								"name": "cycle_478",
								"type": "signal t_sample",
								"source": "box: [mul $in1 $in2] => mul_476"
							},
							{
								"class": "Variable",
								"id": "node_11561",
								"name": "mul_482",
								"type": "signal t_sample",
								"source": "box: [mul $in1 $in2] => mul_476"
							}
						],
						"attributes": {
							
						},
						"type": "signal t_sample",
						"source": "box: [mul $in1 $in2] => mul_476"
					}
				],
				"outputs": [
					{
						"class": "Variable",
						"id": "node_11562",
						"name": "mul_476",
						"type": "signal t_sample",
						"source": "box: [mul $in1 $in2] => mul_476"
					}
				],
				"source": "box: [mul $in1 $in2] => mul_476"
			},
			{
				"class": "Statement",
				"id": "node_11563",
				"inputs": [
					{
						"class": "Expression",
						"id": "node_11564",
						"operator": "add",
						"inputs": [
							{
								"class": "Variable",
								"id": "node_11565",
								"name": "mul_488",
								"type": "signal t_sample",
								"source": "box: [add $in1 $in2] => add_480"
							},
							{
								"class": "Variable",
								"id": "node_11566",
								"name": "mul_476",
								"type": "signal t_sample",
								"source": "box: [add $in1 $in2] => add_480"
							}
						],
						"attributes": {
							
						},
						"type": "signal t_sample",
						"source": "box: [add $in1 $in2] => add_480"
					}
				],
				"outputs": [
					{
						"class": "Variable",
						"id": "node_11567",
						"name": "add_480",
						"type": "signal t_sample",
						"source": "box: [add $in1 $in2] => add_480"
					}
				],
				"source": "box: [add $in1 $in2] => add_480"
			},
			{
				"class": "Statement",
				"id": "node_11568",
				"inputs": [
					{
						"class": "Expression",
						"id": "node_11569",
						"operator": "clamp",
						"inputs": [
							{
								"class": "Variable",
								"id": "node_11570",
								"name": "add_480",
								"type": "signal t_sample",
								"source": "box: [clamp $in1 0 3940] => clamp_481"
							},
							{
								"class": "Constant",
								"id": "node_11571",
								"value": "0",
								"eval": 0,
								"type": "constant int",
								"source": "box: [clamp $in1 0 3940] => clamp_481"
							},
							{
								"class": "Constant",
								"id": "node_11572",
								"value": "3940",
								"eval": 3940,
								"type": "constant int",
								"source": "box: [clamp $in1 0 3940] => clamp_481"
							}
						],
						"attributes": {
							
						},
						"type": "signal t_sample",
						"source": "box: [clamp $in1 0 3940] => clamp_481"
					}
				],
				"outputs": [
					{
						"class": "Variable",
						"id": "node_11573",
						"name": "clamp_481",
						"type": "signal t_sample",
						"source": "box: [clamp $in1 0 3940] => clamp_481"
					}
				],
				"source": "box: [clamp $in1 0 3940] => clamp_481"
			},
			{
				"class": "Statement",
				"id": "node_11574",
				"inputs": [
					{
						"class": "Expression",
						"id": "node_11575",
						"operator": "read",
						"inputs": [
							{
								"class": "Variable",
								"id": "node_11576",
								"name": "delay_484",
								"type": "init Delay",
								"source": "box: [delay 3940 $in1 $in2] => tap_485"
							},
							{
								"class": "Variable",
								"id": "node_11577",
								"name": "clamp_481",
								"type": "signal t_sample",
								"source": "box: [delay 3940 $in1 $in2] => tap_485"
							}
						],
						"attributes": {
							
						},
						"type": "signal t_sample",
						"source": "box: [delay 3940 $in1 $in2] => tap_485"
					}
				],
				"outputs": [
					{
						"class": "Variable",
						"id": "node_11578",
						"name": "tap_485",
						"type": "signal t_sample",
						"source": "box: [delay 3940 $in1 $in2] => tap_485"
					}
				],
				"source": "box: [delay 3940 $in1 $in2] => tap_485"
			},
			{
				"class": "Statement",
				"id": "node_11579",
				"inputs": [
					{
						"class": "Expression",
						"id": "node_11580",
						"operator": "add",
						"inputs": [
							{
								"class": "Variable",
								"id": "node_11581",
								"name": "switch_462",
								"type": "signal t_sample",
								"source": "box: [add $in1 $in2] => add_460"
							},
							{
								"class": "Variable",
								"id": "node_11582",
								"name": "tap_485",
								"type": "signal t_sample",
								"source": "box: [add $in1 $in2] => add_460"
							}
						],
						"attributes": {
							
						},
						"type": "signal t_sample",
						"source": "box: [add $in1 $in2] => add_460"
					}
				],
				"outputs": [
					{
						"class": "Variable",
						"id": "node_11583",
						"name": "add_460",
						"type": "signal t_sample",
						"source": "box: [add $in1 $in2] => add_460"
					}
				],
				"source": "box: [add $in1 $in2] => add_460"
			},
			{
				"class": "Statement",
				"id": "node_11584",
				"inputs": [
					{
						"class": "Expression",
						"id": "node_11585",
						"operator": "div",
						"inputs": [
							{
								"class": "Variable",
								"id": "node_11586",
								"name": "add_460",
								"type": "signal t_sample",
								"source": "box: [div $in1 2] => div_458"
							},
							{
								"class": "Constant",
								"id": "node_11587",
								"value": "2",
								"eval": 2,
								"type": "constant int",
								"source": "box: [div $in1 2] => div_458"
							}
						],
						"attributes": {
							
						},
						"type": "signal t_sample",
						"source": "box: [div $in1 2] => div_458"
					}
				],
				"outputs": [
					{
						"class": "Variable",
						"id": "node_11588",
						"name": "div_458",
						"type": "signal t_sample",
						"source": "box: [div $in1 2] => div_458"
					}
				],
				"source": "box: [div $in1 2] => div_458"
			},
			{
				"class": "Statement",
				"id": "node_11589",
				"inputs": [
					{
						"class": "Expression",
						"id": "node_11590",
						"operator": "add",
						"inputs": [
							{
								"class": "Variable",
								"id": "node_11591",
								"name": "div_458",
								"type": "signal t_sample",
								"source": "join: [out 2 $in1] =>  1"
							},
							{
								"class": "Variable",
								"id": "node_11592",
								"name": "gate_471",
								"type": "signal t_sample",
								"source": "join: [out 2 $in1] =>  1"
							}
						],
						"attributes": {
							
						},
						"type": "signal t_sample",
						"source": "join: [out 2 $in1] =>  1"
					}
				],
				"outputs": [
					{
						"class": "Variable",
						"id": "node_11593",
						"name": "out2",
						"type": "signal t_sample",
						"source": "box: [out 2 $in1] => "
					}
				],
				"source": "box: [out 2 $in1] => "
			},
			{
				"class": "Statement",
				"id": "node_11594",
				"inputs": [
					{
						"class": "Expression",
						"id": "node_11595",
						"operator": "mul",
						"inputs": [
							{
								"class": "Variable",
								"id": "node_11596",
								"name": "tap_485",
								"type": "signal t_sample",
								"source": "box: [mul $in1 $in2] => mul_483"
							},
							{
								"class": "Variable",
								"id": "node_11597",
								"name": "mul_486",
								"type": "control t_sample",
								"source": "box: [mul $in1 $in2] => mul_483"
							}
						],
						"attributes": {
							
						},
						"type": "signal t_sample",
						"source": "box: [mul $in1 $in2] => mul_483"
					}
				],
				"outputs": [
					{
						"class": "Variable",
						"id": "node_11598",
						"name": "mul_483",
						"type": "signal t_sample",
						"source": "box: [mul $in1 $in2] => mul_483"
					}
				],
				"source": "box: [mul $in1 $in2] => mul_483"
			},
			{
				"class": "Statement",
				"id": "node_11599",
				"inputs": [
					{
						"class": "Expression",
						"id": "node_11600",
						"operator": "read",
						"inputs": [
							{
								"class": "Variable",
								"id": "node_11601",
								"name": "delay_489",
								"type": "init Delay",
								"source": "box: [delay 3840 $in1 $in2] => tap_490"
							},
							{
								"class": "Variable",
								"id": "node_11602",
								"name": "clamp_481",
								"type": "signal t_sample",
								"source": "box: [delay 3840 $in1 $in2] => tap_490"
							}
						],
						"attributes": {
							
						},
						"type": "signal t_sample",
						"source": "box: [delay 3840 $in1 $in2] => tap_490"
					}
				],
				"outputs": [
					{
						"class": "Variable",
						"id": "node_11603",
						"name": "tap_490",
						"type": "signal t_sample",
						"source": "box: [delay 3840 $in1 $in2] => tap_490"
					}
				],
				"source": "box: [delay 3840 $in1 $in2] => tap_490"
			},
			{
				"class": "Statement",
				"id": "node_11604",
				"inputs": [
					{
						"class": "Expression",
						"id": "node_11605",
						"operator": "add",
						"inputs": [
							{
								"class": "Variable",
								"id": "node_11606",
								"name": "switch_462",
								"type": "signal t_sample",
								"source": "box: [add $in1 $in2] => add_461"
							},
							{
								"class": "Variable",
								"id": "node_11607",
								"name": "tap_490",
								"type": "signal t_sample",
								"source": "box: [add $in1 $in2] => add_461"
							}
						],
						"attributes": {
							
						},
						"type": "signal t_sample",
						"source": "box: [add $in1 $in2] => add_461"
					}
				],
				"outputs": [
					{
						"class": "Variable",
						"id": "node_11608",
						"name": "add_461",
						"type": "signal t_sample",
						"source": "box: [add $in1 $in2] => add_461"
					}
				],
				"source": "box: [add $in1 $in2] => add_461"
			},
			{
				"class": "Statement",
				"id": "node_11609",
				"inputs": [
					{
						"class": "Expression",
						"id": "node_11610",
						"operator": "div",
						"inputs": [
							{
								"class": "Variable",
								"id": "node_11611",
								"name": "add_461",
								"type": "signal t_sample",
								"source": "box: [div $in1 2] => div_459"
							},
							{
								"class": "Constant",
								"id": "node_11612",
								"value": "2",
								"eval": 2,
								"type": "constant int",
								"source": "box: [div $in1 2] => div_459"
							}
						],
						"attributes": {
							
						},
						"type": "signal t_sample",
						"source": "box: [div $in1 2] => div_459"
					}
				],
				"outputs": [
					{
						"class": "Variable",
						"id": "node_11613",
						"name": "div_459",
						"type": "signal t_sample",
						"source": "box: [div $in1 2] => div_459"
					}
				],
				"source": "box: [div $in1 2] => div_459"
			},
			{
				"class": "Statement",
				"id": "node_11614",
				"inputs": [
					{
						"class": "Expression",
						"id": "node_11615",
						"operator": "add",
						"inputs": [
							{
								"class": "Variable",
								"id": "node_11616",
								"name": "div_459",
								"type": "signal t_sample",
								"source": "join: [out 1 $in1] =>  1"
							},
							{
								"class": "Variable",
								"id": "node_11617",
								"name": "gate_471",
								"type": "signal t_sample",
								"source": "join: [out 1 $in1] =>  1"
							}
						],
						"attributes": {
							
						},
						"type": "signal t_sample",
						"source": "join: [out 1 $in1] =>  1"
					}
				],
				"outputs": [
					{
						"class": "Variable",
						"id": "node_11618",
						"name": "out1",
						"type": "signal t_sample",
						"source": "box: [out 1 $in1] => "
					}
				],
				"source": "box: [out 1 $in1] => "
			},
			{
				"class": "Statement",
				"id": "node_11619",
				"inputs": [
					{
						"class": "Expression",
						"id": "node_11620",
						"operator": "mul",
						"inputs": [
							{
								"class": "Variable",
								"id": "node_11621",
								"name": "tap_490",
								"type": "signal t_sample",
								"source": "box: [mul $in1 $in2] => mul_487"
							},
							{
								"class": "Variable",
								"id": "node_11622",
								"name": "mul_486",
								"type": "control t_sample",
								"source": "box: [mul $in1 $in2] => mul_487"
							}
						],
						"attributes": {
							
						},
						"type": "signal t_sample",
						"source": "box: [mul $in1 $in2] => mul_487"
					}
				],
				"outputs": [
					{
						"class": "Variable",
						"id": "node_11623",
						"name": "mul_487",
						"type": "signal t_sample",
						"source": "box: [mul $in1 $in2] => mul_487"
					}
				],
				"source": "box: [mul $in1 $in2] => mul_487"
			},
			{
				"class": "Statement",
				"id": "node_11624",
				"inputs": [
					{
						"class": "Variable",
						"id": "node_11625",
						"name": "history_467_next_469",
						"type": "signal t_sample",
						"source": "box: [history history_467 0 $in1] => history_467"
					}
				],
				"outputs": [
					{
						"class": "Variable",
						"id": "node_11626",
						"name": "history_467",
						"type": "signal t_sample",
						"source": "box: [history history_467 0 $in1] => history_467"
					}
				],
				"source": "source: [gen $in1 @file swtoggle] => gen_470 parent: box: [history history_467 0 $in1] => history_467"
			},
			{
				"class": "Statement",
				"id": "node_11665",
				"inputs": [
					{
						"class": "Variable",
						"id": "node_11666",
						"name": "history_448_next_450",
						"type": "signal t_sample",
						"source": "box: [history history_448 0 $in1] => history_448"
					}
				],
				"outputs": [
					{
						"class": "Variable",
						"id": "node_11667",
						"name": "history_448",
						"type": "signal t_sample",
						"source": "box: [history history_448 0 $in1] => history_448"
					}
				],
				"source": "source: [gen $in1 @file oopsy.ctrl.smooth3] => gen_454 parent: box: [history history_448 0 $in1] => history_448"
			},
			{
				"class": "Statement",
				"id": "node_11662",
				"inputs": [
					{
						"class": "Variable",
						"id": "node_11663",
						"name": "history_444_next_452",
						"type": "signal t_sample",
						"source": "box: [history history_444 0 $in1] => history_444"
					}
				],
				"outputs": [
					{
						"class": "Variable",
						"id": "node_11664",
						"name": "history_444",
						"type": "signal t_sample",
						"source": "box: [history history_444 0 $in1] => history_444"
					}
				],
				"source": "source: [gen $in1 @file oopsy.ctrl.smooth3] => gen_454 parent: box: [history history_444 0 $in1] => history_444"
			},
			{
				"class": "Statement",
				"id": "node_11659",
				"inputs": [
					{
						"class": "Variable",
						"id": "node_11660",
						"name": "history_446_next_451",
						"type": "signal t_sample",
						"source": "box: [history history_446 0 $in1] => history_446"
					}
				],
				"outputs": [
					{
						"class": "Variable",
						"id": "node_11661",
						"name": "history_446",
						"type": "signal t_sample",
						"source": "box: [history history_446 0 $in1] => history_446"
					}
				],
				"source": "source: [gen $in1 @file oopsy.ctrl.smooth3] => gen_454 parent: box: [history history_446 0 $in1] => history_446"
			},
			{
				"class": "Statement",
				"id": "node_11656",
				"inputs": [
					{
						"class": "Variable",
						"id": "node_11657",
						"name": "history_448_next_499",
						"type": "signal t_sample",
						"source": "box: [history history_448 0 $in1] => history_448"
					}
				],
				"outputs": [
					{
						"class": "Variable",
						"id": "node_11658",
						"name": "history_503",
						"type": "signal t_sample",
						"source": "box: [history history_448 0 $in1] => history_448"
					}
				],
				"source": "source: [gen $in1 @file oopsy.ctrl.smooth3] => gen_455 parent: box: [history history_448 0 $in1] => history_448"
			},
			{
				"class": "Statement",
				"id": "node_11653",
				"inputs": [
					{
						"class": "Variable",
						"id": "node_11654",
						"name": "history_444_next_497",
						"type": "signal t_sample",
						"source": "box: [history history_444 0 $in1] => history_444"
					}
				],
				"outputs": [
					{
						"class": "Variable",
						"id": "node_11655",
						"name": "history_504",
						"type": "signal t_sample",
						"source": "box: [history history_444 0 $in1] => history_444"
					}
				],
				"source": "source: [gen $in1 @file oopsy.ctrl.smooth3] => gen_455 parent: box: [history history_444 0 $in1] => history_444"
			},
			{
				"class": "Statement",
				"id": "node_11650",
				"inputs": [
					{
						"class": "Variable",
						"id": "node_11651",
						"name": "history_446_next_498",
						"type": "signal t_sample",
						"source": "box: [history history_446 0 $in1] => history_446"
					}
				],
				"outputs": [
					{
						"class": "Variable",
						"id": "node_11652",
						"name": "history_505",
						"type": "signal t_sample",
						"source": "box: [history history_446 0 $in1] => history_446"
					}
				],
				"source": "source: [gen $in1 @file oopsy.ctrl.smooth3] => gen_455 parent: box: [history history_446 0 $in1] => history_446"
			},
			{
				"class": "Statement",
				"id": "node_11646",
				"inputs": [
					{
						"class": "Expression",
						"id": "node_11647",
						"operator": "write",
						"inputs": [
							{
								"class": "Variable",
								"id": "node_11648",
								"name": "delay_463",
								"type": "init Delay",
								"source": "box: [delay 3840 $in1 $in2] => tap_464"
							},
							{
								"class": "Variable",
								"id": "node_11649",
								"name": "gate_472",
								"type": "signal t_sample",
								"source": "box: [delay 3840 $in1 $in2] => tap_464"
							}
						],
						"attributes": {
							
						},
						"type": "signal void",
						"source": "box: [delay 3840 $in1 $in2] => tap_464"
					}
				],
				"outputs": {
					
				},
				"source": "box: [delay 3840 $in1 $in2] => tap_464"
			},
			{
				"class": "Statement",
				"id": "node_11643",
				"inputs": [
					{
						"class": "Variable",
						"id": "node_11644",
						"name": "history_448_next_509",
						"type": "signal t_sample",
						"source": "box: [history history_448 0 $in1] => history_448"
					}
				],
				"outputs": [
					{
						"class": "Variable",
						"id": "node_11645",
						"name": "history_516",
						"type": "signal t_sample",
						"source": "box: [history history_448 0 $in1] => history_448"
					}
				],
				"source": "source: [gen $in1 @file oopsy.ctrl.smooth3] => gen_453 parent: box: [history history_448 0 $in1] => history_448"
			},
			{
				"class": "Statement",
				"id": "node_11640",
				"inputs": [
					{
						"class": "Variable",
						"id": "node_11641",
						"name": "history_444_next_511",
						"type": "signal t_sample",
						"source": "box: [history history_444 0 $in1] => history_444"
					}
				],
				"outputs": [
					{
						"class": "Variable",
						"id": "node_11642",
						"name": "history_517",
						"type": "signal t_sample",
						"source": "box: [history history_444 0 $in1] => history_444"
					}
				],
				"source": "source: [gen $in1 @file oopsy.ctrl.smooth3] => gen_453 parent: box: [history history_444 0 $in1] => history_444"
			},
			{
				"class": "Statement",
				"id": "node_11637",
				"inputs": [
					{
						"class": "Variable",
						"id": "node_11638",
						"name": "history_446_next_512",
						"type": "signal t_sample",
						"source": "box: [history history_446 0 $in1] => history_446"
					}
				],
				"outputs": [
					{
						"class": "Variable",
						"id": "node_11639",
						"name": "history_518",
						"type": "signal t_sample",
						"source": "box: [history history_446 0 $in1] => history_446"
					}
				],
				"source": "source: [gen $in1 @file oopsy.ctrl.smooth3] => gen_453 parent: box: [history history_446 0 $in1] => history_446"
			},
			{
				"class": "Statement",
				"id": "node_11633",
				"inputs": [
					{
						"class": "Expression",
						"id": "node_11634",
						"operator": "write",
						"inputs": [
							{
								"class": "Variable",
								"id": "node_11635",
								"name": "delay_484",
								"type": "init Delay",
								"source": "box: [delay 3940 $in1 $in2] => tap_485"
							},
							{
								"class": "Variable",
								"id": "node_11636",
								"name": "mul_487",
								"type": "signal t_sample",
								"source": "box: [delay 3940 $in1 $in2] => tap_485"
							}
						],
						"attributes": {
							
						},
						"type": "signal void",
						"source": "box: [delay 3940 $in1 $in2] => tap_485"
					}
				],
				"outputs": {
					
				},
				"source": "box: [delay 3940 $in1 $in2] => tap_485"
			},
			{
				"class": "Statement",
				"id": "node_11627",
				"inputs": [
					{
						"class": "Expression",
						"id": "node_11628",
						"operator": "write",
						"inputs": [
							{
								"class": "Variable",
								"id": "node_11629",
								"name": "delay_489",
								"type": "init Delay",
								"source": "box: [delay 3840 $in1 $in2] => tap_490"
							},
							{
								"class": "Expression",
								"id": "node_11630",
								"operator": "add",
								"inputs": [
									{
										"class": "Variable",
										"id": "node_11631",
										"name": "mul_483",
										"type": "signal t_sample",
										"source": "join: [delay 3840 $in1 $in2] => tap_490 1"
									},
									{
										"class": "Variable",
										"id": "node_11632",
										"name": "gate_472",
										"type": "signal t_sample",
										"source": "join: [delay 3840 $in1 $in2] => tap_490 1"
									}
								],
								"attributes": {
									
								},
								"type": "signal t_sample",
								"source": "join: [delay 3840 $in1 $in2] => tap_490 1"
							}
						],
						"attributes": {
							
						},
						"type": "signal void",
						"source": "box: [delay 3840 $in1 $in2] => tap_490"
					}
				],
				"outputs": {
					
				},
				"source": "box: [delay 3840 $in1 $in2] => tap_490"
			}
		]
	},
	"source": "patcher: gen.patcher 0x7fb72598eb70 graph 0x600002b14680"
}